guenv/__init__.py
guenv/cli.py
guenv/utils.py
guenv-0.0.4.dist-info/LICENSE.txt
guenv-0.0.4.dist-info/METADATA
guenv-0.0.4.dist-info/WHEEL
guenv-0.0.4.dist-info/entry_points.txt
guenv-0.0.4.dist-info/top_level.txt
guenv-0.0.4.dist-info/RECORD
