Metadata-Version: 2.1
Name: guenv
Version: 0.0.4
Summary: UNKNOWN
Home-page: UNKNOWN
Author: kouml
License: Copyright (c) kouml
Requires-Dist: click
Provides-Extra: develop
Requires-Dist: click ; extra == 'develop'
